bluarchive/__init__.py
bluarchive/bluarchive.py
bluarchive-0.2.dist-info/LICENSE.txt
bluarchive-0.2.dist-info/METADATA
bluarchive-0.2.dist-info/WHEEL
bluarchive-0.2.dist-info/entry_points.txt
bluarchive-0.2.dist-info/top_level.txt
bluarchive-0.2.dist-info/RECORD
