Metadata-Version: 2.1
Name: bluarchive
Version: 0.2
Summary: Download purchased content from Bluprint (formerly Craftsy)
Home-page: https://github.com/half-duplex/bluarchive
Author: Trevor Bergeron
Author-email: bluarchive@sec.gd
License: CC BY-NC-SA 4.0
Platform: UNKNOWN
Classifier: Development Status :: 4 - Beta
Classifier: Operating System :: OS Independent
Classifier: Topic :: System :: Archiving :: Backup
Requires-Python: >=3.6, <4
Requires-Dist: requests
Provides-Extra: dev
Requires-Dist: black ; extra == 'dev'
Requires-Dist: flake8 ; extra == 'dev'
Requires-Dist: flake8-coding ; extra == 'dev'
Requires-Dist: flake8-import-order ; extra == 'dev'
